<?xml version="1.0" encoding="UTF-8"?>
<!--
    This XML file allows us to easily customize the look and language used
    in our program's user interface. Note that this properties file is only
    for the standard controls for an app from the Desktop Java Framework, so
    it would not include things initialized for the workspace, which is
    customizable.
-->
<properties>
    <property_list>
        <property name="APP_TITLE"	    value="Code Check"></property>
    	<property name="APP_LOGO"	    value="CodeCheck.png"></property>
        <property name="UNTITLED_CHECK_TEXT"	    value="Untitled CodeCheck"></property>
    	<property name="APP_PATH_CSS"	    value="style/"></property>
    	<property name="APP_CSS"	    value="cc_style.css"></property>
        <property name="APP_PATH_WORK"      value="work/"></property>
        <property name="APP_TM_TEXT"		value="TM"></property>
        <property name="APP_VERSION"		value="0.0.9-6b (build 2)"></property>
        <property name="APP_PERSISTENT_DATA"		value="persistentData.json"></property>

        <!-- PROJECT DIRS -->
        <property name="BLACKBOARD"	    value="blackboard"></property>
        <property name="SUBMISSIONS"	    value="submissions"></property>
        <property name="CODE"	    value="code"></property>
        <property name="PROJECTS"	    value="projects"></property>

        <!-- PROGRAM ICON FILES -->
        <property name="NEW_ICON"	    value="New.png"></property>
        <property name="LOAD_ICON"	    value="load.png"></property>
        <property name="PREV_BUTTON_ICON"	    value="prev.png"></property>
        <property name="NEXT_BUTTON_ICON"	    value="next.png"></property>
        <property name="HOME_BUTTON_ICON"	    value="home.png"></property>
        <property name="ABOUT_BUTTON_ICON"	    value="about.png"></property>
        <property name="RENAME_BUTTON_ICON"	    value="rename.png"></property>
        <property name="REFRESH_BUTTON_ICON"	    value="refresh.png"></property>
        <property name="VIEW_BUTTON_ICON"	    value="view.png"></property>
        <property name="REMOVE_BUTTON_ICON"	    value="remove.png"></property>

        <!-- TOOLTIPS FOR BUTTONS -->
        <property name="NEW_TOOLTIP"		value="Create new Code Check"></property>
        <property name="LOAD_TOOLTIP"		value="Load an existing Code Check"></property>
        <property name="PREV_BUTTON_TOOLTIP"		value="Go to previous step"></property>
        <property name="NEXT_BUTTON_TOOLTIP"		value="Go to next step"></property>
        <property name="HOME_BUTTON_TOOLTIP"		value="Go to first step"></property>
        <property name="REMOVE_BUTTON_TOOLTIP"		value="Remove selected file"></property>
        <property name="VIEW_BUTTON_TOOLTIP"		value="View selected file"></property>
        <property name="REFRESH_BUTTON_TOOLTIP"		value="Refresh list"></property>

        <!-- LABELS -->
        <property name="STEP_1_TITLE"		value="Step 1: Extract Submissions"></property>
        <property name="STEP_2_TITLE"		value="Step 2: Rename Student Submissions"></property>
        <property name="STEP_3_TITLE"		value="Step 3: Unzip Student Submissions"></property>
        <property name="STEP_4_TITLE"		value="Step 4: Extract Source Code"></property>
        <property name="STEP_5_TITLE"		value="Step 5: Code Check"></property>
        <property name="STEP_1_HINT"		value="Select the submissions below from which to extract student work"></property>
        <property name="STEP_2_HINT"		value="Click the Rename button to rename all submissions"></property>
        <property name="STEP_3_HINT"		value="Select student submissions and click Unzip"></property>
        <property name="STEP_4_HINT"		value="Select students and click Extract Code"></property>
        <property name="STEP_5_HINT"		value="Select students and click Code Check"></property>
        <property name="STEP_1_LIST_TITLE"		value="Blackboard Submissions"></property>
        <property name="STEP_2_LIST_TITLE"		value="Student Submissions"></property>
        <property name="STEP_3_LIST_TITLE"		value="Student ZIP Files"></property>
        <property name="STEP_4_LIST_TITLE"		value="Student Work Directories"></property>
        <property name="STEP_5_LIST_TITLE"		value="Student Work"></property>
        <property name="STEP_1_PROGRESS"		value="Extraction Progress"></property>
        <property name="STEP_2_PROGRESS"		value="Rename Progress"></property>
        <property name="STEP_3_PROGRESS"		value="Unzip Progress"></property>
        <property name="STEP_4_PROGRESS"		value="Code Progress"></property>
        <property name="STEP_5_PROGRESS"		value="Check Progress"></property>
        <property name="FILE_TYPE_LABEL"		value="Source File Types"></property>
        <property name="FILE_TYPE_1"		value=".java"></property>
        <property name="FILE_TYPE_2"		value=".c, .h, .cpp"></property>
        <property name="FILE_TYPE_3"		value=".js"></property>
        <property name="FILE_TYPE_4"		value=".cs"></property>
        <property name="FILE_TYPE_CUSTOM"		value="Enter source type(s)"></property>
        <property name="WELCOME_VIEW_RECENTS_HEADER_TEXT"		value="Recent Work"></property>
        <property name="WELCOME_VIEW_NEW_BUTTON_TEXT"		value=""></property>
        <property name="NEW_DIALOG_TITLE_TEXT"		value="Create New Code Check"></property>
        <property name="NEW_DIALOG_PROMPT_TEXT"		value="Code Check Name"></property>
        <property name="NEW_DIALOG_HEADER_TEXT"		value="New Code Check"></property>
        <property name="NEW_DIALOG_CONTENT_TEXT"		value="Enter Code Check name"></property>
        <property name="NEW_DIALOG_ERROR_TEXT"		value="Error: file exists"></property>
        <property name="NEW_DIALOG_EMPTY_TEXT"		value="Name cannot be blank"></property>
        <property name="RENAME_DIALOG_TITLE_TEXT"		value="Rename"></property>
        <property name="RENAME_DIALOG_PROMPT_TEXT"		value="Code Check Name"></property>
        <property name="RENAME_DIALOG_HEADER_TEXT"		value="Rename Code Check"></property>
        <property name="RENAME_DIALOG_CONTENT_TEXT"		value="Enter new name"></property>
        <property name="WELCOME_TO_TEXT"		value="Welcome to"></property>
        <property name="ABOUT_LABEL_TEXT"		value="About"></property>
        <property name="VERSION_TEXT"		value="Version"></property>
        <property name="LEGAL_NOTICE"		value="Copyright © 2017"></property>
        <property name="AUTHOR_TEXT"		value="Created By Daniel Niyazov"></property>
        <property name="QUIT_DIALOG_TITLE_TEXT"		value="Quit"></property>
        <property name="QUIT_DIALOG_HEADER_TEXT"		value="Close Code Check?"></property>
        <property name="QUIT_DIALOG_CONTENT_TEXT"		value="Are you sure you wish to close this application?"></property>
        <property name="SUCCESS_EXTRACT_MESSAGE"		value="Successfully extracted files:"></property>
        <property name="FAIL_EXTRACT_MESSAGE"		value="Submission Errors:"></property>
        <property name="SUCCESS_RENAME_MESSAGE"		value="Successfully renamed submissions:"></property>
        <property name="FAIL_RENAME_MESSAGE"		value="Rename Errors:"></property>
        <property name="SUCCESS_UNZIP_MESSAGE"		value="Successfully unzipped files:"></property>
        <property name="FAIL_UNZIP_MESSAGE"		value="Unzip Errors:"></property>
        <property name="SUCCESS_CODE_EXTRACT_MESSAGE"		value="Successful code extraction:"></property>
        <property name="FAIL_CODE_EXTRACT_MESSAGE"		value="Code Extraction Errors:"></property>
        <property name="CORRUPT_CHECK_HEADER"		value="Corrupt Code Check"></property>
        <property name="CORRUPT_CHECK_MESSAGE"		value="The selected CodeCheck is corrupt or invalid."></property>
        <property name="NO_SELECTION_TITLE"		value="Oops"></property>
        <property name="NO_SELECTION_MESSAGE"		value="No files types selected."></property>
        <property name="STEP_COMPLETE_TEXT"		value=" has completed."></property>
        <property name="FILE_VIEWER_TITLE"		value="File Viewer"></property>
        <property name="FILE_TYPE_DIRECTORY"		value="File Type: Directory"></property>
        <property name="FILE_TYPE_ZIP"		value="File Type: Zip Archive"></property>
        <property name="FILE_VIEWER_HEADER"		value="Contents of "></property>
        <property name="CHECK_COMPLETE_MESSAGE"		value="Student Plagiarism results can be found at"></property>

        <!-- ERROR MESSAGES -->
        <property name="CLOSE_BUTTON_TEXT"              value="Close"></property>

        <property name="NEW_ERROR_MESSAGE"              value="An error occured creating New work."></property>
        <property name="NEW_ERROR_TITLE"		value="New Work Error"></property>
        <property name="LOAD_ERROR_MESSAGE"             value="An error occured loading work."></property>
        <property name="LOAD_ERROR_TITLE"		value="Load Work Error"></property>
        <property name="SAVE_ERROR_MESSAGE"             value="An error occured saving work."></property>
        <property name="SAVE_ERROR_TITLE"		value="Save Work Error"></property>
        <property name="PROPERTIES_LOAD_ERROR_MESSAGE"	value="An error occured loading a properties file."></property>
        <property name="PROPERTIES_LOAD_ERROR_TITLE"	value="Properties File Loading Error"></property>
        <property name="ZIP_ERROR_TITLE"	value="Zip Error"></property>
        <property name="ZIP_ERROR_MESSAGE"	value="An error occured unzipping "></property>
        <property name="DELETE_PROMPT_HEADER"	value="Delete "></property>
        <property name="DELETE_PROMPT_MESSAGE"	value="This is a permanent action. Are you sure?"></property>
        <property name="STEP_IN_PROGRESS_HEADER"	value="Action in progress"></property>
        <property name="STEP_IN_PROGRESS_MESSAGE"	value="There is already an action in progress, please wait until it is complete before you continue."></property>

        <!-- VERIFICATION MESSAGES -->

        <property name="NEW_COMPLETED_MESSAGE"		value="New Work Ready for Editing"></property>
        <property name="NEW_COMPLETED_TITLE"		value="New Work Created"></property>
        <property name="LOAD_COMPLETED_MESSAGE"		value="File Loading Completed and ready for editing"></property>
        <property name="LOAD_COMPLETED_TITLE"		value="Loading Completed"></property>
        <property name="SAVE_COMPLETED_MESSAGE"		value="File Saving Completed"></property>
        <property name="SAVE_COMPLETED_TITLE"		value="Saving Completed"></property>
        <property name="SAVE_UNSAVED_WORK_MESSAGE"	value="Would you like to save your unsaved work first?"></property>
        <property name="SAVE_UNSAVED_WORK_TITLE"	value="Save unsaved work?"></property>

        <property name="NEW_CREATED_MESSAGE"		value="New Work Created but not yet Saved"></property>
        <property name="WORK_LOADED_MESSAGE"		value="The Work has been Loaded"></property>
        <property name="WORK_SAVED_MESSAGE"		value="The Work has been Saved"></property>
        <property name="SAVE_UNSAVED_WORK_MESSAGE"	value="Do you want to save your unsaved work first?"></property>
    	<property name="SAVE_WORK_TITLE"		value="Save your work"></property>
    	<property name="LOAD_WORK_TITLE"		value="Select file to load"></property>
    	<property name="WORK_FILE_EXT"			value="cck"></property>
    	<property name="WORK_FILE_EXT_DESC"		value="Code Check File"></property>

        <!-- WORKSPACE CONTROLS STUFF -->
        <property name="PREV_BUTTON_TEXT"		value="Previous"></property>
        <property name="NEXT_BUTTON_TEXT"		value="Next"></property>
        <property name="HOME_BUTTON_TEXT"		value="Home"></property>
        <property name="RENAME_BUTTON_TEXT"		value="Rename"></property>
        <property name="ABOUT_BUTTON_TEXT"		value="About"></property>
        <property name="STEP_1_BUTTON_1_TEXT"		value="Extract"></property>
        <property name="STEP_2_BUTTON_1_TEXT"		value="Rename"></property>
        <property name="STEP_3_BUTTON_1_TEXT"		value="Unzip"></property>
        <property name="STEP_4_BUTTON_1_TEXT"		value="Extract Code"></property>
        <property name="STEP_5_BUTTON_1_TEXT"		value="Code Check"></property>
        <property name="STEP_5_BUTTON_2_TEXT"		value="View Results"></property>

        <!-- WORKSPACE ERROR MESSAGES -->
        <property name="INVALID_IMAGE_PATH_TITLE"       value="Invalid Image Path"></property>
        <property name="INVALID_IMAGE_PATH_MESSAGE"     value="Image not found"></property>
    </property_list>
    <property_options_list>
    </property_options_list>
</properties>
